{
    "title": "HttpProblemSchema",
    "description": "See https://datatracker.ietf.org/doc/draft-ietf-appsawg-http-problem/",
    "type": "object",
    "allOf": [
        {
            "$ref": "./VersionedContext.schema.json"
        },
        {
            "properties": {
                "type": {
                    "type": "string",
                    "description": "A URI reference [RFC3986] that identifies the problem type. When dereferenced, it is encouraged to provide human-readable documentation for the problem type (e.g., using  HTML [W3C.REC-html401-19991224]).",
                    "pattern": "^https?:\\/\\/(((?:[a-z0-9](?:[a-z0-9-]{0,61}[a-z0-9])?\\.)+[a-z0-9][a-z0-9-]{0,61}[a-z0-9])|((?:(?:25[0-5]|2[0-4][0-9]|[01]?[0-9][0-9]?)\\.){3}(?:25[0-5]|2[0-4][0-9]|[01]?[0-9][0-9]?)))(:(6553[0-5]|655[0-2]\\d|65[0-4]\\d\\d|6[0-4]\\d{3}|[1-5]\\d{4}|[1-9]\\d{0,3}|0))?(\\/[-a-zA-Z0-9@:%_+.,~?&/=()]*)*(#(?:[^#^[\\]{}\\\\\"<>%\\s]|%[0-9a-f]{2})*)*$"
                },
                "title": {
                    "type": "string",
                    "description": "A short, human-readable summary of the problem type."
                },
                "status": {
                    "type": "integer",
                    "description": "The HTTP status code (RFC7231, Section 6) generated by the origin server for this occurrence of the problem.",
                    "minimum": 100,
                    "maximum": 599,
                    "format": "int32"
                },
                "detail": {
                    "type": "string",
                    "description": "An human readable explanation specific to this occurrence of the problem."
                }
            },
            "additionalProperties": false,
            "required": [
                "type",
                "title",
                "status"
            ]
        }
    ]
}
